delphixpy
delphixpy/v1_10_0
delphixpy/v1_10_0/web
delphixpy/v1_10_0/web/about
delphixpy/v1_10_0/web/action
delphixpy/v1_10_0/web/alert
delphixpy/v1_10_0/web/alert/profile
delphixpy/v1_10_0/web/analytics
delphixpy/v1_10_0/web/analytics/statistic
delphixpy/v1_10_0/web/authorization
delphixpy/v1_10_0/web/authorization/configuration
delphixpy/v1_10_0/web/capacity
delphixpy/v1_10_0/web/capacity/consumer
delphixpy/v1_10_0/web/capacity/consumer/historical
delphixpy/v1_10_0/web/capacity/group
delphixpy/v1_10_0/web/capacity/group/historical
delphixpy/v1_10_0/web/capacity/snapshot
delphixpy/v1_10_0/web/capacity/system
delphixpy/v1_10_0/web/capacity/system/historical
delphixpy/v1_10_0/web/connectivity
delphixpy/v1_10_0/web/data
delphixpy/v1_10_0/web/database
delphixpy/v1_10_0/web/database/performanceHistory
delphixpy/v1_10_0/web/database/template
delphixpy/v1_10_0/web/delphix
delphixpy/v1_10_0/web/domain
delphixpy/v1_10_0/web/environment
delphixpy/v1_10_0/web/environment/oracle
delphixpy/v1_10_0/web/environment/oracle/clusternode
delphixpy/v1_10_0/web/environment/oracle/listener
delphixpy/v1_10_0/web/environment/user
delphixpy/v1_10_0/web/environment/windows
delphixpy/v1_10_0/web/environment/windows/availabilitygrouplistener
delphixpy/v1_10_0/web/environment/windows/clusterinstance
delphixpy/v1_10_0/web/environment/windows/clusternode
delphixpy/v1_10_0/web/environment/windows/failoverclusterrepositoryinstance
delphixpy/v1_10_0/web/environment/windows/failoverclusterrepositorylistener
delphixpy/v1_10_0/web/fault
delphixpy/v1_10_0/web/fault/effect
delphixpy/v1_10_0/web/group
delphixpy/v1_10_0/web/host
delphixpy/v1_10_0/web/host/privilegeElevation
delphixpy/v1_10_0/web/host/privilegeElevation/profile
delphixpy/v1_10_0/web/host/privilegeElevation/profileScript
delphixpy/v1_10_0/web/job
delphixpy/v1_10_0/web/maskingjob
delphixpy/v1_10_0/web/maskingjob/serviceconfig
delphixpy/v1_10_0/web/namespace
delphixpy/v1_10_0/web/network
delphixpy/v1_10_0/web/network/dsp
