Metadata-Version: 2.1
Name: delphixpy
Version: 1.11.9.0
Summary: Delphix Client Bindings
Home-page: http://www.delphix.com
Author: Delphix
Author-email: support@delphix.com
License: UNKNOWN
Platform: UNKNOWN
Classifier: Programming Language :: Python :: 2
Classifier: Programming Language :: Python :: 3
Classifier: License :: OSI Approved :: Apache Software License
